README.md
setup.py
src/gpuled/__init__.py
src/gpuled/gpuled.py
src/gpuled.egg-info/PKG-INFO
src/gpuled.egg-info/SOURCES.txt
src/gpuled.egg-info/dependency_links.txt
src/gpuled.egg-info/top_level.txt