Metadata-Version: 2.1
Name: gpuled
Version: 1.0.0
Summary: use led to show GPU temp
Home-page: https://github.com/ousyouyou/gpuled
Author: OuSyouyou
Author-email: s2122011@stu.musashino-u.ac.jp
License: UNKNOWN
Platform: UNKNOWN
Classifier: Programming Language :: Python :: 3
Classifier: License :: OSI Approved :: MIT License
Classifier: Operating System :: OS Independent
Requires-Python: >=3.6
